{
  "발화정보" : {
    "stt" : "유투브에서 겨울왕국을 열 번도 더 본 것 같아요 ",
    "scriptId" : "소아남녀-00224",
    "fileNm" : "소아남여_소아남여01_F_1592501389-0_9_수도권_실내_00224.wav",
    "recrdTime" : "7.170",
    "recrdQuality" : "16K",
    "recrdDt" : "2021-01-13 22:15:12",
    "scriptSetNo" : "T_소아남녀_1"
  },
  "대화정보" : {
    "recrdEnvrn" : "실내",
    "colctUnitCode" : "AI 챗봇",
    "cityCode" : "수도권",
    "recrdUnit" : "iOS",
    "convrsThema" : "자기가 좋아하는 것 소개"
  },
  "녹음자정보" : {
    "gender" : "여",
    "recorderId" : "1592501389-0",
    "age" : 9
  }
}