{
  "발화정보" : {
    "stt" : "그런데 현대에 들어서면서 육류 섭취가 늘어나고 그것 때문에 변이 단단해져서 변비가 생기(SP:기) 시작한 거더라고",
    "scriptId" : "일반통합-06820",
    "fileNm" : "일반남여_일반통합06_F_1524374974_25_수도권_실내_06820.wav",
    "recrdTime" : "10.320",
    "recrdQuality" : "16K",
    "recrdDt" : "2020-12-30 23:55:15",
    "scriptSetNo" : "T_일반통합_6"
  },
  "대화정보" : {
    "recrdEnvrn" : "실내",
    "colctUnitCode" : "AI 챗봇",
    "cityCode" : "수도권",
    "recrdUnit" : "Windows 10",
    "convrsThema" : "변비에 좋은 음식"
  },
  "녹음자정보" : {
    "gender" : "여",
    "recorderId" : "1524374974",
    "age" : 25
  }
}